dsproject/__init__.py
dsproject/math_utils.py
dsproject/string_utils.py
studentutils-0.1.0.dist-info/METADATA
studentutils-0.1.0.dist-info/WHEEL
studentutils-0.1.0.dist-info/top_level.txt
studentutils-0.1.0.dist-info/RECORD
