Metadata-Version: 2.4
Name: studentutils
Version: 0.1.0
Summary: Simple student utilities library
Author: MUHAMMAD AHMAD - GHAUS ALI - MUHAMMAD SHAHZAIB HANJRA
Author-email: s2024332008@umt.edu.pk - s2024332030@umt.edu.pk - s2024332027@umt.edu.pk
Requires-Python: >=3.6
Dynamic: author
Dynamic: author-email
Dynamic: requires-python
Dynamic: summary
